pyLasaDataset/__init__.py
pyLasaDataset/dataset.py
pyLasaDataset/utilities.py
pyLasaDataset/resources/LASAHandwritingDataset/DataSet/Angle.mat
pyLasaDataset/resources/LASAHandwritingDataset/DataSet/BendedLine.mat
pyLasaDataset/resources/LASAHandwritingDataset/DataSet/CShape.mat
pyLasaDataset/resources/LASAHandwritingDataset/DataSet/DoubleBendedLine.mat
pyLasaDataset/resources/LASAHandwritingDataset/DataSet/GShape.mat
pyLasaDataset/resources/LASAHandwritingDataset/DataSet/JShape.mat
pyLasaDataset/resources/LASAHandwritingDataset/DataSet/JShape_2.mat
pyLasaDataset/resources/LASAHandwritingDataset/DataSet/Khamesh.mat
pyLasaDataset/resources/LASAHandwritingDataset/DataSet/LShape.mat
pyLasaDataset/resources/LASAHandwritingDataset/DataSet/Leaf_1.mat
pyLasaDataset/resources/LASAHandwritingDataset/DataSet/Leaf_2.mat
pyLasaDataset/resources/LASAHandwritingDataset/DataSet/Line.mat
pyLasaDataset/resources/LASAHandwritingDataset/DataSet/Multi_Models_1.mat
pyLasaDataset/resources/LASAHandwritingDataset/DataSet/Multi_Models_2.mat
pyLasaDataset/resources/LASAHandwritingDataset/DataSet/Multi_Models_3.mat
pyLasaDataset/resources/LASAHandwritingDataset/DataSet/Multi_Models_4.mat
pyLasaDataset/resources/LASAHandwritingDataset/DataSet/NShape.mat
pyLasaDataset/resources/LASAHandwritingDataset/DataSet/PShape.mat
pyLasaDataset/resources/LASAHandwritingDataset/DataSet/RShape.mat
pyLasaDataset/resources/LASAHandwritingDataset/DataSet/Saeghe.mat
pyLasaDataset/resources/LASAHandwritingDataset/DataSet/Sharpc.mat
pyLasaDataset/resources/LASAHandwritingDataset/DataSet/Sine.mat
pyLasaDataset/resources/LASAHandwritingDataset/DataSet/Snake.mat
pyLasaDataset/resources/LASAHandwritingDataset/DataSet/Spoon.mat
pyLasaDataset/resources/LASAHandwritingDataset/DataSet/Sshape.mat
pyLasaDataset/resources/LASAHandwritingDataset/DataSet/Trapezoid.mat
pyLasaDataset/resources/LASAHandwritingDataset/DataSet/WShape.mat
pyLasaDataset/resources/LASAHandwritingDataset/DataSet/Worm.mat
pyLasaDataset-0.1.1.dist-info/METADATA
pyLasaDataset-0.1.1.dist-info/WHEEL
pyLasaDataset-0.1.1.dist-info/top_level.txt
pyLasaDataset-0.1.1.dist-info/RECORD
