Metadata-Version: 2.1
Name: pyLasaDataset
Version: 0.1.1
Summary: LASA Handwriting dataset loader and other tools for Python.
Home-page: https://github.com/justagist/pyLasaDataset
Author: Saif Sidhik
Author-email: mail@saifsidhik.page
License: Public Domain
Project-URL: Bug Tracker, https://github.com/justagist/pylasadataset/issues
Project-URL: Documentation, https://github.com/justagist/pyLasaDataset/blob/master/README.md
Project-URL: Source Code, https://github.com/justagist/pylasadataset
Keywords: handwriting dataset,python
Platform: UNKNOWN
Classifier: License :: Public Domain
Classifier: Topic :: Software Development :: Libraries :: Python Modules
